indexify_text_splitter-0.1.3.dist-info/METADATA
indexify_text_splitter-0.1.3.dist-info/WHEEL
indexify_text_splitter/__init__.py
indexify_text_splitter/indexify_text_splitter.pypy310-pp73-x86-linux-gnu.so
indexify_text_splitter-0.1.3.dist-info/RECORD
